Pre/1-verilog/verilog vscode/former/practice.v
module practice (
    output c
);
    reg a;
    reg b;
    assign c = a & b;
//==================//上面是源代码，下面是生成测试vcd文件的代码
    initial begin            
        $dumpfile("practice.vcd");        //生成的vcd文件名称
        $dumpvars(0, practice);    //模块名称
        a <= 1;
        b <= 1;
        # 6000 $finish;
    end
    always begin
        #20 a = ~a;                 // 每20个单位clock取反
    end
endmodule //practice

Pre/1-verilog/verilog vscode/former/practice.vcd
$date
	Sat Sep 18 16:07:31 2021
$end
$version
	Icarus Verilog
$end
$timescale
	1s
$end
$scope module practice $end
$var wire 1 ! c $end
$var reg 1 " a $end
$var reg 1 # b $end
$upscope $end
$enddefinitions $end
#0
$dumpvars
1#
1"
1!
$end
#20
0!
0"
#40
1!
1"
#60
0!
0"
#80
1!
1"
#100
0!
0"
#120
1!
1"
#140
0!
0"
#160
1!
1"
#180
0!
0"
#200
1!
1"
#220
0!
0"
#240
1!
1"
#260
0!
0"
#280
1!
1"
#300
0!
0"
#320
1!
1"
#340
0!
0"
#360
1!
1"
#380
0!
0"
#400
1!
1"
#420
0!
0"
#440
1!
1"
#460
0!
0"
#480
1!
1"
#500
0!
0"
#520
1!
1"
#540
0!
0"
#560
1!
1"
#580
0!
0"
#600
1!
1"
#620
0!
0"
#640
1!
1"
#660
0!
0"
#680
1!
1"
#700
0!
0"
#720
1!
1"
#740
0!
0"
#760
1!
1"
#780
0!
0"
#800
1!
1"
#820
0!
0"
#840
1!
1"
#860
0!
0"
#880
1!
1"
#900
0!
0"
#920
1!
1"
#940
0!
0"
#960
1!
1"
#980
0!
0"
#1000
1!
1"
#1020
0!
0"
#1040
1!
1"
#1060
0!
0"
#1080
1!
1"
#1100
0!
0"
#1120
1!
1"
#1140
0!
0"
#1160
1!
1"
#1180
0!
0"
#1200
1!
1"
#1220
0!
0"
#1240
1!
1"
#1260
0!
0"
#1280
1!
1"
#1300
0!
0"
#1320
1!
1"
#1340
0!
0"
#1360
1!
1"
#1380
0!
0"
#1400
1!
1"
#1420
0!
0"
#1440
1!
1"
#1460
0!
0"
#1480
1!
1"
#1500
0!
0"
#1520
1!
1"
#1540
0!
0"
#1560
1!
1"
#1580
0!
0"
#1600
1!
1"
#1620
0!
0"
#1640
1!
1"
#1660
0!
0"
#1680
1!
1"
#1700
0!
0"
#1720
1!
1"
#1740
0!
0"
#1760
1!
1"
#1780
0!
0"
#1800
1!
1"
#1820
0!
0"
#1840
1!
1"
#1860
0!
0"
#1880
1!
1"
#1900
0!
0"
#1920
1!
1"
#1940
0!
0"
#1960
1!
1"
#1980
0!
0"
#2000
1!
1"
#2020
0!
0"
#2040
1!
1"
#2060
0!
0"
#2080
1!
1"
#2100
0!
0"
#2120
1!
1"
#2140
0!
0"
#2160
1!
1"
#2180
0!
0"
#2200
1!
1"
#2220
0!
0"
#2240
1!
1"
#2260
0!
0"
#2280
1!
1"
#2300
0!
0"
#2320
1!
1"
#2340
0!
0"
#2360
1!
1"
#2380
0!
0"
#2400
1!
1"
#2420
0!
0"
#2440
1!
1"
#2460
0!
0"
#2480
1!
1"
#2500
0!
0"
#2520
1!
1"
#2540
0!
0"
#2560
1!
1"
#2580
0!
0"
#2600
1!
1"
#2620
0!
0"
#2640
1!
1"
#2660
0!
0"
#2680
1!
1"
#2700
0!
0"
#2720
1!
1"
#2740
0!
0"
#2760
1!
1"
#2780
0!
0"
#2800
1!
1"
#2820
0!
0"
#2840
1!
1"
#2860
0!
0"
#2880
1!
1"
#2900
0!
0"
#2920
1!
1"
#2940
0!
0"
#2960
1!
1"
#2980
0!
0"
#3000
1!
1"
#3020
0!
0"
#3040
1!
1"
#3060
0!
0"
#3080
1!
1"
#3100
0!
0"
#3120
1!
1"
#3140
0!
0"
#3160
1!
1"
#3180
0!
0"
#3200
1!
1"
#3220
0!
0"
#3240
1!
1"
#3260
0!
0"
#3280
1!
1"
#3300
0!
0"
#3320
1!
1"
#3340
0!
0"
#3360
1!
1"
#3380
0!
0"
#3400
1!
1"
#3420
0!
0"
#3440
1!
1"
#3460
0!
0"
#3480
1!
1"
#3500
0!
0"
#3520
1!
1"
#3540
0!
0"
#3560
1!
1"
#3580
0!
0"
#3600
1!
1"
#3620
0!
0"
#3640
1!
1"
#3660
0!
0"
#3680
1!
1"
#3700
0!
0"
#3720
1!
1"
#3740
0!
0"
#3760
1!
1"
#3780
0!
0"
#3800
1!
1"
#3820
0!
0"
#3840
1!
1"
#3860
0!
0"
#3880
1!
1"
#3900
0!
0"
#3920
1!
1"
#3940
0!
0"
#3960
1!
1"
#3980
0!
0"
#4000
1!
1"
#4020
0!
0"
#4040
1!
1"
#4060
0!
0"
#4080
1!
1"
#4100
0!
0"
#4120
1!
1"
#4140
0!
0"
#4160
1!
1"
#4180
0!
0"
#4200
1!
1"
#4220
0!
0"
#4240
1!
1"
#4260
0!
0"
#4280
1!
1"
#4300
0!
0"
#4320
1!
1"
#4340
0!
0"
#4360
1!
1"
#4380
0!
0"
#4400
1!
1"
#4420
0!
0"
#4440
1!
1"
#4460
0!
0"
#4480
1!
1"
#4500
0!
0"
#4520
1!
1"
#4540
0!
0"
#4560
1!
1"
#4580
0!
0"
#4600
1!
1"
#4620
0!
0"
#4640
1!
1"
#4660
0!
0"
#4680
1!
1"
#4700
0!
0"
#4720
1!
1"
#4740
0!
0"
#4760
1!
1"
#4780
0!
0"
#4800
1!
1"
#4820
0!
0"
#4840
1!
1"
#4860
0!
0"
#4880
1!
1"
#4900
0!
0"
#4920
1!
1"
#4940
0!
0"
#4960
1!
1"
#4980
0!
0"
#5000
1!
1"
#5020
0!
0"
#5040
1!
1"
#5060
0!
0"
#5080
1!
1"
#5100
0!
0"
#5120
1!
1"
#5140
0!
0"
#5160
1!
1"
#5180
0!
0"
#5200
1!
1"
#5220
0!
0"
#5240
1!
1"
#5260
0!
0"
#5280
1!
1"
#5300
0!
0"
#5320
1!
1"
#5340
0!
0"
#5360
1!
1"
#5380
0!
0"
#5400
1!
1"
#5420
0!
0"
#5440
1!
1"
#5460
0!
0"
#5480
1!
1"
#5500
0!
0"
#5520
1!
1"
#5540
0!
0"
#5560
1!
1"
#5580
0!
0"
#5600
1!
1"
#5620
0!
0"
#5640
1!
1"
#5660
0!
0"
#5680
1!
1"
#5700
0!
0"
#5720
1!
1"
#5740
0!
0"
#5760
1!
1"
#5780
0!
0"
#5800
1!
1"
#5820
0!
0"
#5840
1!
1"
#5860
0!
0"
#5880
1!
1"
#5900
0!
0"
#5920
1!
1"
#5940
0!
0"
#5960
1!
1"
#5980
0!
0"
#6000
1!
1"
